{"doc_idx":340,"tokens":["replace","holding","wrench","fitting"],"mentions":[{"start":0,"end":1,"labels":["Activity"]},{"start":1,"end":2,"labels":["Specifier"]},{"start":2,"end":3,"labels":["Item"]},{"start":3,"end":4,"labels":["Consumable"]}]}
{"doc_idx":341,"tokens":["front","jacks","will","not","work"],"mentions":[{"start":0,"end":1,"labels":["Location"]},{"start":1,"end":2,"labels":["Item"]},{"start":2,"end":5,"labels":["Observation/Observed_state"]}]}
{"doc_idx":342,"tokens":["front","jacks","wont","raise"],"mentions":[{"start":0,"end":1,"labels":["Location"]},{"start":1,"end":2,"labels":["Item"]},{"start":2,"end":4,"labels":["Observation/Observed_state"]}]}
{"doc_idx":343,"tokens":["front","l","\\","h","side","jack","proxy","u","\\","s"],"mentions":[{"start":0,"end":1,"labels":["Location"]},{"start":1,"end":4,"labels":["Location"]},{"start":4,"end":5,"labels":["Location"]},{"start":5,"end":6,"labels":["Item"]},{"start":6,"end":7,"labels":["Item"]}]}
{"doc_idx":344,"tokens":["front","ladder","bent"],"mentions":[{"start":0,"end":1,"labels":["Location"]},{"start":1,"end":2,"labels":["Item"]},{"start":2,"end":3,"labels":["Observation/Observed_state"]}]}
{"doc_idx":345,"tokens":["front","levelling","cyl","control","cable","u/s"],"mentions":[{"start":0,"end":1,"labels":["Location"]},{"start":1,"end":2,"labels":["Specifier"]},{"start":2,"end":3,"labels":["Item"]},{"start":3,"end":5,"labels":["Item"]}]}
{"doc_idx":346,"tokens":["front","levelling","jack","light","not","coming","on"],"mentions":[{"start":0,"end":1,"labels":["Location"]},{"start":1,"end":2,"labels":["Specifier"]},{"start":2,"end":3,"labels":["Item"]},{"start":3,"end":4,"labels":["Item"]},{"start":4,"end":7,"labels":["Observation/Observed_state"]}]}
{"doc_idx":347,"tokens":["front","levelling","jack","limit","switch","faulty"],"mentions":[{"start":0,"end":1,"labels":["Location"]},{"start":1,"end":2,"labels":["Specifier"]},{"start":2,"end":3,"labels":["Item"]},{"start":3,"end":5,"labels":["Item"]},{"start":5,"end":6,"labels":["Observation/Observed_state"]}]}
{"doc_idx":348,"tokens":["front","levelling","jacks","creeping"],"mentions":[{"start":0,"end":1,"labels":["Location"]},{"start":1,"end":2,"labels":["Specifier"]},{"start":2,"end":3,"labels":["Item"]},{"start":3,"end":4,"labels":["Observation/Qualitative"]}]}
{"doc_idx":349,"tokens":["front","levelling","jacks","creeping","down"],"mentions":[{"start":0,"end":1,"labels":["Location"]},{"start":1,"end":2,"labels":["Specifier"]},{"start":2,"end":3,"labels":["Item"]},{"start":3,"end":4,"labels":["Observation/Qualitative"]},{"start":4,"end":5,"labels":["Location"]}]}
{"doc_idx":350,"tokens":["front","light","u/s"],"mentions":[{"start":0,"end":1,"labels":["Location"]},{"start":1,"end":2,"labels":["Item"]}]}
{"doc_idx":351,"tokens":["repair","air","supply","to","thread","lube"],"mentions":[{"start":0,"end":1,"labels":["Activity"]},{"start":1,"end":3,"labels":["Item"]},{"start":4,"end":6,"labels":["Consumable"]}]}
{"doc_idx":352,"tokens":["repair","alternator"],"mentions":[{"start":0,"end":1,"labels":["Activity"]},{"start":1,"end":2,"labels":["Item"]}]}
{"doc_idx":353,"tokens":["repair","alternator","adjusting","bracket"],"mentions":[{"start":0,"end":1,"labels":["Activity"]},{"start":1,"end":2,"labels":["Item"]},{"start":2,"end":3,"labels":["Specifier"]},{"start":3,"end":4,"labels":["Item"]}]}
{"doc_idx":354,"tokens":["repair","and","adjust","pipe","guide"],"mentions":[{"start":0,"end":1,"labels":["Activity"]},{"start":2,"end":3,"labels":["Activity"]},{"start":3,"end":4,"labels":["Item"]},{"start":4,"end":5,"labels":["Item"]}]}
{"doc_idx":355,"tokens":["repair","and","fab","drill","signage"],"mentions":[{"start":0,"end":1,"labels":["Activity"]},{"start":2,"end":3,"labels":["Activity","Abbreviation"]},{"start":3,"end":4,"labels":["Item"]},{"start":4,"end":5,"labels":["Item"]}]}
{"doc_idx":356,"tokens":["repair","and","re-certify","separator","tank"],"mentions":[{"start":0,"end":1,"labels":["Activity"]},{"start":2,"end":3,"labels":["Activity"]},{"start":3,"end":4,"labels":["Item"]},{"start":4,"end":5,"labels":["Item"]}]}
{"doc_idx":357,"tokens":["repair","and","replace","comp.","discharge","hose"],"mentions":[{"start":0,"end":1,"labels":["Activity"]},{"start":2,"end":3,"labels":["Activity"]},{"start":3,"end":4,"labels":["Item","Abbreviation"]},{"start":4,"end":5,"labels":["Specifier"]},{"start":5,"end":6,"labels":["Item"]}]}
{"doc_idx":358,"tokens":["repair","and","return","d90","air","end"],"mentions":[{"start":0,"end":1,"labels":["Activity"]},{"start":2,"end":3,"labels":["Activity"]},{"start":4,"end":5,"labels":["Unsure"]},{"start":5,"end":6,"labels":["Item"]}]}
{"doc_idx":359,"tokens":["repair","and","return","d90","track"],"mentions":[{"start":0,"end":1,"labels":["Activity"]},{"start":2,"end":3,"labels":["Activity"]},{"start":4,"end":5,"labels":["Item"]}]}
{"doc_idx":360,"tokens":["repair","and","return","d90","track","ass."],"mentions":[{"start":0,"end":1,"labels":["Activity"]},{"start":2,"end":3,"labels":["Activity"]},{"start":4,"end":6,"labels":["Item"]}]}
{"doc_idx":361,"tokens":["repair","thred","lube"],"mentions":[{"start":0,"end":1,"labels":["Activity"]},{"start":1,"end":3,"labels":["Consumable"]}]}
{"doc_idx":362,"tokens":["repair","to","auto","fire","supression"],"mentions":[{"start":0,"end":1,"labels":["Activity"]},{"start":2,"end":3,"labels":["Specifier"]},{"start":3,"end":5,"labels":["Item"]}]}
{"doc_idx":363,"tokens":["repair","to","chain","guide"],"mentions":[{"start":0,"end":1,"labels":["Activity"]},{"start":2,"end":4,"labels":["Item"]}]}
{"doc_idx":364,"tokens":["repair","to","chip","deflector"],"mentions":[{"start":0,"end":1,"labels":["Activity"]},{"start":2,"end":4,"labels":["Item"]}]}
{"doc_idx":365,"tokens":["repair","to","handrails"],"mentions":[{"start":0,"end":1,"labels":["Activity"]},{"start":2,"end":3,"labels":["Item"]}]}
{"doc_idx":366,"tokens":["repair","to","lack","retract","sensor"],"mentions":[{"start":0,"end":1,"labels":["Activity"]},{"start":2,"end":3,"labels":["Unsure"]},{"start":3,"end":4,"labels":["Item"]},{"start":4,"end":5,"labels":["Item"]}]}
{"doc_idx":367,"tokens":["repair","to","mast","cracking"],"mentions":[{"start":0,"end":1,"labels":["Activity"]},{"start":2,"end":3,"labels":["Item"]},{"start":3,"end":4,"labels":["Observation/Observed_state"]}]}
{"doc_idx":368,"tokens":["repair","to","planemrepair","to","planem"],"mentions":[{"start":0,"end":1,"labels":["Activity"]},{"start":2,"end":3,"labels":["Item","Typo","Unsure"]},{"start":4,"end":5,"labels":["Item","Typo","Unsure"]}]}
{"doc_idx":369,"tokens":["repair","to","radio","power","supply"],"mentions":[{"start":0,"end":1,"labels":["Activity"]},{"start":2,"end":3,"labels":["Item"]},{"start":3,"end":5,"labels":["Item"]}]}
{"doc_idx":370,"tokens":["repair","top","of","carousel","spider","ITEM_ID"],"mentions":[{"start":0,"end":1,"labels":["Activity"]},{"start":1,"end":3,"labels":["Location"]},{"start":3,"end":4,"labels":["Item"]},{"start":4,"end":5,"labels":["Item"]}]}
{"doc_idx":371,"tokens":["damaged"],"mentions":[{"start":0,"end":1,"labels":["Observation/Observed_state"]}]}
{"doc_idx":372,"tokens":["damaged","chain","gaurd"],"mentions":[{"start":0,"end":1,"labels":["Observation/Observed_state"]},{"start":1,"end":2,"labels":["Item"]},{"start":2,"end":3,"labels":["Item"]}]}
{"doc_idx":373,"tokens":["damaged","electrical","cable","on","ITEM_ID"],"mentions":[{"start":0,"end":1,"labels":["Observation/Observed_state"]},{"start":1,"end":3,"labels":["Item"]},{"start":3,"end":4,"labels":["Location"]}]}
{"doc_idx":374,"tokens":["damaged","hyd","hose","break","out","fork"],"mentions":[{"start":0,"end":1,"labels":["Observation/Observed_state"]},{"start":1,"end":3,"labels":["Item"]},{"start":3,"end":5,"labels":["Item"]},{"start":5,"end":6,"labels":["Item"]}]}
{"doc_idx":375,"tokens":["damaged","hydraulic","hoses"],"mentions":[{"start":0,"end":1,"labels":["Observation/Observed_state"]},{"start":1,"end":3,"labels":["Item"]}]}
{"doc_idx":376,"tokens":["damaged","l/h","track","link"],"mentions":[{"start":0,"end":1,"labels":["Observation/Observed_state"]},{"start":1,"end":2,"labels":["Location"]},{"start":2,"end":3,"labels":["Item"]},{"start":3,"end":4,"labels":["Item"]}]}
{"doc_idx":377,"tokens":["danaged","rope","cover","lower","left"],"mentions":[{"start":0,"end":1,"labels":["Observation/Observed_state","Typo"]},{"start":1,"end":2,"labels":["Item"]},{"start":2,"end":3,"labels":["Item"]},{"start":3,"end":5,"labels":["Location"]}]}
{"doc_idx":378,"tokens":["dangerous","t/tronics","(","positioner",")"],"mentions":[{"start":0,"end":1,"labels":["Observation/Observed_state"]},{"start":1,"end":2,"labels":["Item","Abbreviation"]},{"start":3,"end":4,"labels":["Item"]}]}
{"doc_idx":379,"tokens":["dash","lights","out"],"mentions":[{"start":0,"end":2,"labels":["Item"]},{"start":2,"end":3,"labels":["Observation/Observed_state"]}]}